[{"a": 1, "ar": "لِإِيلَـٰفِ قُرَيْشٍ", "en": "For the accustomed security of the Quraysh¹ -", "sv": "SÅ ATT Quraysh kunde förbli enade och trygga,"}, {"a": 2, "ar": "إِۦلَـٰفِهِمْ رِحْلَةَ ٱلشِّتَآءِ وَٱلصَّيْفِ", "en": "Their accustomed security [in] the caravan of winter and summer¹ -", "sv": "enade och trygga vad gäller såväl deras vinter- som deras sommarfärder."}, {"a": 3, "ar": "فَلْيَعْبُدُوا۟ رَبَّ هَـٰذَا ٱلْبَيْتِ", "en": "Let them worship the Lord of this House,¹", "sv": "Därför skall de tillbe Herren till denna Helgedom,"}, {"a": 4, "ar": "ٱلَّذِىٓ أَطْعَمَهُم مِّن جُوعٍ وَءَامَنَهُم مِّنْ خَوْفٍۭ", "en": "Who has fed them, [saving them] from hunger and made them safe, [saving them] from fear.", "sv": "som har gett dem föda när hungersnöden hotade och trygghet när fruktan hade fått makt över deras [sinnen]."}]