[{"a": 1, "ar": "قُلْ أَعُوذُ بِرَبِّ ٱلنَّاسِ", "en": "Say, \"I seek refuge in the Lord of mankind,", "sv": "SÄG: \"Jag söker skydd hos människornas Herre,"}, {"a": 2, "ar": "مَلِكِ ٱلنَّاسِ", "en": "The Sovereign of mankind,", "sv": "människornas Konung,"}, {"a": 3, "ar": "إِلَـٰهِ ٱلنَّاسِ", "en": "The God of mankind,", "sv": "människornas Gud,"}, {"a": 4, "ar": "مِن شَرِّ ٱلْوَسْوَاسِ ٱلْخَنَّاسِ", "en": "From the evil of the retreating whisperer¹ -", "sv": "mot det onda som den förrädiske frestaren"}, {"a": 5, "ar": "ٱلَّذِى يُوَسْوِسُ فِى صُدُورِ ٱلنَّاسِ", "en": "Who whispers [evil] into the breasts of mankind -", "sv": "viskar i människornas hjärtan,"}, {"a": 6, "ar": "مِنَ ٱلْجِنَّةِ وَٱلنَّاسِ", "en": "From among the jinn and mankind\".¹", "sv": "[viskar] genom [onda] osynliga väsen och [deras likar bland] människorna.\""}]